lowmind/__init__.py
lowmind/lowmind.py
lowmind-0.5.0.dist-info/licenses/LICENSE
lowmind-0.5.0.dist-info/METADATA
lowmind-0.5.0.dist-info/WHEEL
lowmind-0.5.0.dist-info/top_level.txt
lowmind-0.5.0.dist-info/RECORD
